my_package/__init__.py
my_package/database.py
my_package/utils.py
tests/__init__.py
tests/test_database.py
mydbpackage_mysql-0.2.0.dist-info/METADATA
mydbpackage_mysql-0.2.0.dist-info/WHEEL
mydbpackage_mysql-0.2.0.dist-info/entry_points.txt
mydbpackage_mysql-0.2.0.dist-info/top_level.txt
mydbpackage_mysql-0.2.0.dist-info/RECORD
