Metadata-Version: 2.1
Name: mydbpackage-mysql
Version: 0.2.0
Requires-Dist: mysql-connector-python
